README.md
setup.py
servo_lock/__init__.py
servo_lock/servo.py
servo_lock.egg-info/PKG-INFO
servo_lock.egg-info/SOURCES.txt
servo_lock.egg-info/dependency_links.txt
servo_lock.egg-info/entry_points.txt
servo_lock.egg-info/top_level.txt