Metadata-Version: 2.1
Name: servo-lock
Version: 0.0.1.6
Summary: Servo utility for the MG996R; but any servo works.
Home-page: https://github.com/Tsangares/lock_servo
Author-email: william.wyatt@cgu.edu
License: UNKNOWN
Platform: UNKNOWN
Classifier: Programming Language :: Python :: 3
Classifier: License :: OSI Approved :: MIT License
Classifier: Operating System :: OS Independent
Requires-Python: >=3.7
